gsewidgets/__init__.py
gsewidgets/_version.py
gsewidgets/examples/__init__.py
gsewidgets/examples/controller/__init__.py
gsewidgets/examples/controller/main_controller.py
gsewidgets/examples/model/__init__.py
gsewidgets/examples/model/path_model.py
gsewidgets/examples/widget/__init__.py
gsewidgets/examples/widget/example_widget.py
gsewidgets/examples/widget/main_widget.py
gsewidgets/tests/__init__.py
gsewidgets/tests/buttons/__init__.py
gsewidgets/tests/buttons/test_abstract_browser_button.py
gsewidgets/tests/buttons/test_flat_button.py
gsewidgets/widgets/__init__.py
gsewidgets/widgets/buttons.py
gsewidgets/widgets/checkboxes.py
gsewidgets/widgets/comboboxes.py
gsewidgets/widgets/filters.py
gsewidgets/widgets/inputboxes.py
gsewidgets/widgets/labels.py
gsewidgets/widgets/lines.py
gsewidgets/widgets/messageboxes.py
gsewidgets/widgets/spinboxes.py
gsewidgets/widgets/tables.py
gsewidgets-0.0.2.dist-info/licenses/LICENSE
gsewidgets-0.0.2.dist-info/METADATA
gsewidgets-0.0.2.dist-info/WHEEL
gsewidgets-0.0.2.dist-info/top_level.txt
gsewidgets-0.0.2.dist-info/RECORD
