Metadata-Version: 2.4
Name: GSEWidgets
Version: 0.0.2
Summary: Collection of gui widgets to be used in GSE software.
Home-page: https://github.com/GSECARS/GSEWidgets
Author: Christofanis Skordas
Author-email: skordasc@uchicago.edu
Project-URL: Bug Tracker, https://github.com/GSECARS/GSEWidgets/issues
Classifier: Intended Audience :: Science/Research
Classifier: Operating System :: OS Independent
Classifier: Programming Language :: Python :: 3
Classifier: Programming Language :: Python :: 3 :: Only
Classifier: Programming Language :: Python :: 3.10
Classifier: License :: OSI Approved :: GNU General Public License v3 (GPLv3)
Classifier: Topic :: Scientific/Engineering
Requires-Python: >=3.10
License-File: LICENSE
Requires-Dist: PyQt6>=6.4.0
Requires-Dist: qtpy>=2.2.1
Dynamic: license-file
